xlsx2json/__init__.py
xlsx2json/cli.py
xlsx2json-0.0.5.dist-info/DESCRIPTION.rst
xlsx2json-0.0.5.dist-info/METADATA
xlsx2json-0.0.5.dist-info/RECORD
xlsx2json-0.0.5.dist-info/WHEEL
xlsx2json-0.0.5.dist-info/entry_points.txt
xlsx2json-0.0.5.dist-info/metadata.json
xlsx2json-0.0.5.dist-info/top_level.txt
