Metadata-Version: 2.0
Name: xlsx2json
Version: 0.0.5
Summary: Convert XLSX to JSON and include hyperlinks.
Home-page: https://code.datadais.com/
Author: Data Dais
Author-email: code@datadais.com
License: UNKNOWN
Platform: UNKNOWN
Requires-Dist: Click
Requires-Dist: six
Requires-Dist: backports.tempfile
Requires-Dist: openpyxl
